yesmaster/__init__.py
yesmaster/algo/__init__.py
yesmaster/algo/compatible.py
yesmaster/algo/compatible_4in1.py
yesmaster/algo/compatible_8in2.py
yesmaster/algo/one_step_ahead.py
yesmaster/algo/one_step_ahead_test.py
yesmaster/algo/random_idiot.py
yesmaster/algo/random_no_repeat.py
yesmaster/algo/template.py
yesmaster/utils.py
yesmaster/yesmaster.py
yesmaster-3.0.1.dist-info/entry_points.txt
yesmaster-3.0.1.dist-info/WHEEL
yesmaster-3.0.1.dist-info/METADATA
yesmaster-3.0.1.dist-info/RECORD
